multi_bible_search/__init__.py
multi_bible_search/bible_downloader.py
multi_bible_search/bible_search_adapter.py
multi_bible_search/hashtable.h
multi_bible_search/invalid_version.py
multi_bible_search/memcpy_long.h
multi_bible_search/multi_bible_search.c
multi_bible_search/multi_bible_search.pypy39-pp73-win_amd64.pyd
multi_bible_search/parse_json.h
multi_bible_search/rank.h
multi_bible_search/translate.py
multi_bible_search-2.1.5.dist-info/licenses/LICENSE
multi_bible_search-2.1.5.dist-info/METADATA
multi_bible_search-2.1.5.dist-info/WHEEL
multi_bible_search-2.1.5.dist-info/top_level.txt
multi_bible_search-2.1.5.dist-info/RECORD
