Metadata-Version: 2.4
Name: multi_bible_search
Version: 2.1.5
Summary: A Python package for searching multiple versions of the Bible.
Author: Samuel Howard
License:                     GNU GENERAL PUBLIC LICENSE
Project-URL: Homepage, https://github.com/samhaswon/bible_search
Project-URL: Bug Tracker, https://github.com/samhaswon/bible_search/issues
Keywords: bible search,bible_search,esv,kjv,asv,bible_api,bible,multi_bible_search,spanish_bible,spanish_bible_search
Classifier: Programming Language :: Python :: 3
Classifier: Operating System :: OS Independent
Requires-Python: >=3.7
License-File: LICENSE
Dynamic: license-file
